Renamelater/__init__.py
maorpackage-0.1.dist-info/METADATA
maorpackage-0.1.dist-info/WHEEL
maorpackage-0.1.dist-info/top_level.txt
maorpackage-0.1.dist-info/RECORD
