Metadata-Version: 2.1
Name: maorpackage
Version: 0.1
Summary: package creates a textfile
Home-page: UNKNOWN
Author: Maor Parienty
Author-email: maorpari@gmail.com
License: UNKNOWN
Platform: UNKNOWN
